recc/__init__.py
recc/__main__.py
recc/arguments.py
recc/config.py
recc/entrypoint.py
recc/aio/__init__.py
recc/aio/task.py
recc/aio/watcher_container.py
recc/chrono/__init__.py
recc/chrono/datetime.py
recc/chrono/duration.py
recc/core/__init__.py
recc/core/context.py
recc/core/mixin/__init__.py
recc/core/mixin/context_base.py
recc/core/mixin/context_config.py
recc/core/mixin/context_group.py
recc/core/mixin/context_info.py
recc/core/mixin/context_plugin.py
recc/core/mixin/context_project.py
recc/core/mixin/context_role.py
recc/core/mixin/context_system.py
recc/core/mixin/context_user.py
recc/crypto/__init__.py
recc/crypto/password.py
recc/crypto/signature.py
recc/filesystem/__init__.py
recc/filesystem/permission.py
recc/http/__init__.py
recc/http/http_app.py
recc/http/http_cache_keys.py
recc/http/http_client.py
recc/http/http_cors.py
recc/http/http_data_keys.py
recc/http/http_decorator.py
recc/http/http_errors.py
recc/http/http_interface.py
recc/http/http_packet.py
recc/http/http_parameter.py
recc/http/http_path_keys.py
recc/http/http_payload.py
recc/http/http_plugins_www.py
recc/http/http_query_keys.py
recc/http/http_response.py
recc/http/http_session.py
recc/http/http_status.py
recc/http/http_urls.py
recc/http/http_utils.py
recc/http/http_www.py
recc/http/header/__init__.py
recc/http/header/basic_auth.py
recc/http/header/bearer_auth.py
recc/http/http_query_values/__init__.py
recc/http/http_query_values/op.py
recc/http/path/__init__.py
recc/http/path/common.py
recc/http/path/v1.py
recc/http/path/v2.py
recc/http/v2/__init__.py
recc/http/v2/router_v2.py
recc/http/v2/router_v2_admin.py
recc/http/v2/router_v2_dev.py
recc/http/v2/router_v2_main.py
recc/http/v2/router_v2_plugins.py
recc/http/v2/router_v2_public.py
recc/http/v2/router_v2_self.py
recc/inspect/__init__.py
recc/inspect/member.py
recc/inspect/type_origin.py
recc/limit/__init__.py
recc/limit/integer.py
recc/logging/__init__.py
recc/logging/colored_formatter.py
recc/logging/logging.py
recc/network/__init__.py
recc-2.0.5.dist-info/METADATA
recc-2.0.5.dist-info/WHEEL
recc-2.0.5.dist-info/entry_points.txt
recc-2.0.5.dist-info/top_level.txt
recc-2.0.5.dist-info/RECORD
